{
  "sections": {
    "main_home_hero": {
      "type": "main-home-hero",
      "settings": {
        "image": "https://cdn.shopify.com/s/files/1/0838/6373/2480/files/IMG_2124.jpg?v=1782811182",
        "wordmark": "BUSH RIDING",
        "overlay_opacity": 10
      }
    },
    "home_split_1": {
      "type": "main-home-split",
      "settings": {}
    },
    "home_shop_1": {
      "type": "main-home-shop",
      "blocks": {
        "card_1": { "type": "product_card", "settings": {} },
        "card_2": { "type": "product_card", "settings": {} },
        "card_3": { "type": "product_card", "settings": {} },
        "card_4": { "type": "product_card", "settings": {} }
      },
      "block_order": ["card_1", "card_2", "card_3", "card_4"],
      "settings": {
        "banner_left_label": "Trail Collection",
        "banner_right_label": "First Ride"
      }
    },
    "home_split_2": {
      "type": "main-home-split",
      "settings": {}
    },
    "home_shop_2": {
      "type": "main-home-shop",
      "blocks": {
        "card_1": { "type": "product_card", "settings": {} },
        "card_2": { "type": "product_card", "settings": {} },
        "card_3": { "type": "product_card", "settings": {} },
        "card_4": { "type": "product_card", "settings": {} }
      },
      "block_order": ["card_1", "card_2", "card_3", "card_4"],
      "settings": {
        "banner_left_label": "Womens",
        "banner_right_label": "New Arrivals"
      }
    }
  },
  "order": [
    "main_home_hero",
    "home_split_1",
    "home_shop_1",
    "home_split_2",
    "home_shop_2"
  ]
}
